QGOpt/__init__.py
QGOpt/manifolds/__init__.py
QGOpt/manifolds/base_manifold.py
QGOpt/manifolds/choimatrix.py
QGOpt/manifolds/convert.py
QGOpt/manifolds/densitymatrix.py
QGOpt/manifolds/hermitian.py
QGOpt/manifolds/positivecone.py
QGOpt/manifolds/povm.py
QGOpt/manifolds/stiefel.py
QGOpt/manifolds/utils.py
QGOpt/optimizers/Adam.py
QGOpt/optimizers/LD.py
QGOpt/optimizers/SGD.py
QGOpt/optimizers/__init__.py
tests/__init__.py
tests/test_manifolds.py
tests/test_optimizers.py
tests/test_stiefel.py
QGOpt-1.0.0.dist-info/LICENSE
QGOpt-1.0.0.dist-info/METADATA
QGOpt-1.0.0.dist-info/WHEEL
QGOpt-1.0.0.dist-info/top_level.txt
QGOpt-1.0.0.dist-info/RECORD
