Metadata-Version: 2.1
Name: QGOpt
Version: 1.0.0
Summary: Riemannian optimization for quantum mechanics
Home-page: https://github.com/LuchnikovI/QGOpt
Author: I. Luchnikov, A. Ryzhov, M. Krechetov
Author-email: luchnikovilya@gmail.com
License: UNKNOWN
Platform: UNKNOWN
Classifier: Programming Language :: Python :: 3
Classifier: License :: OSI Approved :: Apache Software License
Classifier: Topic :: Scientific/Engineering :: Mathematics
Classifier: Operating System :: OS Independent
